mojolang/__init__.py
mojolang/main.py
mojolang-0.0.1.dist-info/METADATA
mojolang-0.0.1.dist-info/WHEEL
mojolang-0.0.1.dist-info/RECORD
