Metadata-Version: 2.1
Name: mojolang
Version: 0.0.1
Summary: A toolkit for working with Mojo
Author-email: Ryan Young <dev@ryayoung.com>
Classifier: Development Status :: 3 - Alpha
Classifier: Intended Audience :: Developers
Classifier: License :: OSI Approved :: MIT License
Classifier: Operating System :: OS Independent
Classifier: Programming Language :: Python :: 3.10
Classifier: Programming Language :: Python :: 3.11
Classifier: Topic :: Software Development :: Libraries
